rdp2/__init__.py
rdp2/__init__.pyi
rdp2/py.typed
rdp2/rdp2.cpython-312-aarch64-linux-gnu.so
rdp2-1.2.0.dist-info/METADATA
rdp2-1.2.0.dist-info/WHEEL
rdp2-1.2.0.dist-info/RECORD
