Metadata-Version: 2.4
Name: rdp2
Version: 1.2.0
Summary: A high-performance Python library for the Ramer-Douglass-Peucker algorithm implemented in Rust
Keywords: rdp,ramer,douglas,peucker,line,simplification,rust
License: GPL-3.0-only
Project-URL: Source Code, https://github.com/vassilijnadarajah/rdp2
